MANIFEST.in
setup.py
config/logconfig.yml
config/settings.yml
etc/systemd/system/zymkey-filesystem@.service
examples/zk_app_utils_test.py
examples/zk_crypto_test.py
lib/libzk_app_utils.so
zymkey/__init__.py
zymkey/entrypoints.py
zymkey/exceptions.py
zymkey/filesystem.py
zymkey/module.py
zymkey/settings.py
zymkey/utils.py
zymkey/vault.py
zymkey.egg-info/PKG-INFO
zymkey.egg-info/SOURCES.txt
zymkey.egg-info/dependency_links.txt
zymkey.egg-info/entry_points.txt
zymkey.egg-info/requires.txt
zymkey.egg-info/top_level.txt
zymkey/commands/__init__.py
zymkey/commands/filesystem_create.py
zymkey/commands/filesystem_mount.py
zymkey/commands/filesystem_unmount.py
zymkey/commands/lock.py
zymkey/commands/random.py
zymkey/commands/unlock.py