Metadata-Version: 1.0
Name: zymkey
Version: 0.1.3
Summary: Zymkey utilities
Home-page: https://zymbit.com/
Author: Zymbit, Inc.
Author-email: code@zymbit.com
License: LICENSE
Platform: UNKNOWN
